globopt/__init__.py
globopt/myopic_acquisitions.py
globopt/nonmyopic_acquisitions.py
globopt/problems.py
globopt/regression.py
globopt/sampling.py
globopt-1.0.0.dist-info/LICENSE
globopt-1.0.0.dist-info/METADATA
globopt-1.0.0.dist-info/WHEEL
globopt-1.0.0.dist-info/top_level.txt
globopt-1.0.0.dist-info/RECORD
