Metadata-Version: 2.1
Name: globopt
Version: 1.0.0
Summary: Myopic and Non-Myopic Global Optimization
Author-email: Filippo Airaldi <filippoairaldi@gmail.com>
License: MIT
Project-URL: Homepage, https://github.com/FilippoAiraldi/global-optimization
Project-URL: Bug Tracker, https://github.com/FilippoAiraldi/global-optimization/issues
Keywords: optimization,derivative-free-optimization,rollout,multi-step optimization,radial-basis-function,inverse-distance-weighting
Classifier: Programming Language :: Python
Classifier: Programming Language :: Python :: 3 :: Only
Classifier: Programming Language :: Python :: 3.9
Classifier: Programming Language :: Python :: 3.10
Classifier: Programming Language :: Python :: 3.11
Classifier: Programming Language :: Python :: 3.12
Classifier: License :: OSI Approved :: MIT License
Classifier: Operating System :: OS Independent
Classifier: Intended Audience :: Science/Research
Classifier: Topic :: Scientific/Engineering :: Mathematics
Classifier: Topic :: Scientific/Engineering :: Artificial Intelligence
Requires-Python: >=3.9
License-File: LICENSE
Requires-Dist: torch>=2.1.2
Requires-Dist: botorch>=0.9.5
